LICENSE
MANIFEST.in
README.md
requirements.txt
setup.cfg
setup.py
flask_oojsui/__init__.py
flask_oojsui/functions.py
flask_oojsui.egg-info/PKG-INFO
flask_oojsui.egg-info/SOURCES.txt
flask_oojsui.egg-info/dependency_links.txt
flask_oojsui.egg-info/requires.txt
flask_oojsui.egg-info/top_level.txt
flask_oojsui/static/oojs/oojs.jquery.js
flask_oojsui/static/oojs/oojs.js
flask_oojsui/static/oojs-ui/oojs-ui-apex-icons-alerts.css
flask_oojsui/static/oojs-ui/oojs-ui-apex-icons-alerts.rtl.css
flask_oojsui/static/oojs-ui/oojs-ui-apex-icons-content.css
flask_oojsui/static/oojs-ui/oojs-ui-apex-icons-content.rtl.css
flask_oojsui/static/oojs-ui/oojs-ui-apex-icons-editing-advanced.css
flask_oojsui/static/oojs-ui/oojs-ui-apex-icons-editing-advanced.min.css
flask_oojsui/static/oojs-ui/oojs-ui-apex-icons-editing-advanced.raster.css
flask_oojsui/static/oojs-ui/oojs-ui-apex-icons-editing-advanced.raster.min.css
flask_oojsui/static/oojs-ui/oojs-ui-apex-icons-editing-advanced.raster.rtl.css
flask_oojsui/static/oojs-ui/oojs-ui-apex-icons-editing-advanced.raster.rtl.min.css
flask_oojsui/static/oojs-ui/oojs-ui-apex-icons-editing-advanced.rtl.css
flask_oojsui/static/oojs-ui/oojs-ui-apex-icons-editing-advanced.rtl.min.css
flask_oojsui/static/oojs-ui/oojs-ui-apex-icons-editing-advanced.vector.css
flask_oojsui/static/oojs-ui/oojs-ui-apex-icons-editing-advanced.vector.min.css
flask_oojsui/static/oojs-ui/oojs-ui-apex-icons-editing-advanced.vector.rtl.css
flask_oojsui/static/oojs-ui/oojs-ui-apex-icons-editing-advanced.vector.rtl.min.css
flask_oojsui/static/oojs-ui/oojs-ui-apex-icons-editing-core.css
flask_oojsui/static/oojs-ui/oojs-ui-apex-icons-editing-core.min.css
flask_oojsui/static/oojs-ui/oojs-ui-apex-icons-editing-core.raster.css
flask_oojsui/static/oojs-ui/oojs-ui-apex-icons-editing-core.raster.min.css
flask_oojsui/static/oojs-ui/oojs-ui-apex-icons-editing-core.raster.rtl.css
flask_oojsui/static/oojs-ui/oojs-ui-apex-icons-editing-core.raster.rtl.min.css
flask_oojsui/static/oojs-ui/oojs-ui-apex-icons-editing-core.rtl.css
flask_oojsui/static/oojs-ui/oojs-ui-apex-icons-editing-core.rtl.min.css
flask_oojsui/static/oojs-ui/oojs-ui-apex-icons-editing-core.vector.css
